librovore/data/.gitignore
librovore/data/configuration/general.toml
librovore/__init__.py
librovore/__main__.py
librovore/cacheproxy.py
librovore/cli.py
librovore/detection.py
librovore/exceptions.py
librovore/functions.py
librovore/interfaces.py
librovore/processors.py
librovore/py.typed
librovore/results.py
librovore/search.py
librovore/server.py
librovore/state.py
librovore/urlpatterns.py
librovore/urls.py
librovore/xtnsapi.py
librovore/__/__init__.py
librovore/__/doctab.py
librovore/__/imports.py
librovore/__/inscription.py
librovore/__/interfaces.py
librovore/__/nomina.py
librovore/_typedecls/bs4/__init__.pyi
librovore/_typedecls/bs4/_deprecation.pyi
librovore/_typedecls/bs4/_typing.pyi
librovore/_typedecls/bs4/_warnings.pyi
librovore/_typedecls/bs4/element.pyi
librovore/_typedecls/markdownify/__init__.pyi
librovore/_typedecls/sphobjinv/__init__.pyi
librovore/_typedecls/sphobjinv/__main__.pyi.bak
librovore/_typedecls/sphobjinv/data.pyi.bak
librovore/_typedecls/sphobjinv/enum.pyi.bak
librovore/_typedecls/sphobjinv/error.pyi.bak
librovore/_typedecls/sphobjinv/fileops.pyi.bak
librovore/_typedecls/sphobjinv/inventory.pyi.bak
librovore/_typedecls/sphobjinv/re.pyi.bak
librovore/_typedecls/sphobjinv/schema.pyi.bak
librovore/_typedecls/sphobjinv/version.pyi.bak
librovore/_typedecls/sphobjinv/zlib.pyi.bak
librovore/inventories/__.py
librovore/inventories/__init__.py
librovore/inventories/mkdocs/__.py
librovore/inventories/mkdocs/__init__.py
librovore/inventories/mkdocs/detection.py
librovore/inventories/mkdocs/main.py
librovore/inventories/sphinx/__.py
librovore/inventories/sphinx/__init__.py
librovore/inventories/sphinx/detection.py
librovore/inventories/sphinx/main.py
librovore/structures/__.py
librovore/structures/__init__.py
librovore/structures/mkdocs/__.py
librovore/structures/mkdocs/__init__.py
librovore/structures/mkdocs/conversion.py
librovore/structures/mkdocs/converters.py
librovore/structures/mkdocs/detection.py
librovore/structures/mkdocs/extraction.py
librovore-1.0a7.dist-info/METADATA
librovore-1.0a7.dist-info/WHEEL
librovore-1.0a7.dist-info/entry_points.txt
librovore-1.0a7.dist-info/licenses/LICENSE.txt
librovore-1.0a7.dist-info/RECORD
