Metadata-Version: 2.4
Name: librovore
Version: 1.0a7
Summary: 🐲📚 Librovore - CLI and MCP server for consuming documentation.
Project-URL: Homepage, https://github.com/emcd/python-librovore
Project-URL: Documentation, https://emcd.github.io/python-librovore
Project-URL: Download, https://pypi.org/project/librovore/#files
Project-URL: Source Code, https://github.com/emcd/python-librovore
Project-URL: Issue Tracker, https://github.com/emcd/python-librovore/issues
Author-email: Eric McDonald <emcd@users.noreply.github.com>
License-Expression: Apache-2.0
License-File: LICENSE.txt
Keywords: documentation,mcp,model context protocol,search,sphinx
Classifier: Development Status :: 4 - Beta
Classifier: Intended Audience :: Developers
Classifier: License :: OSI Approved :: Apache Software License
Classifier: Programming Language :: Python :: 3 :: Only
Classifier: Programming Language :: Python :: 3.10
Classifier: Programming Language :: Python :: 3.11
Classifier: Programming Language :: Python :: 3.12
Classifier: Programming Language :: Python :: 3.13
Classifier: Programming Language :: Python :: Implementation :: CPython
Classifier: Programming Language :: Python :: Implementation :: PyPy
Classifier: Topic :: Software Development
Requires-Python: >=3.10
Requires-Dist: absence~=1.1
Requires-Dist: accretive~=4.1
Requires-Dist: beautifulsoup4
Requires-Dist: detextive~=1.0
Requires-Dist: dynadoc~=1.3
Requires-Dist: emcd-appcore[cli]~=1.1
Requires-Dist: exceptiongroup
Requires-Dist: frigid~=4.1
Requires-Dist: httpx
Requires-Dist: lxml
Requires-Dist: markdownify
Requires-Dist: mcp
Requires-Dist: rapidfuzz
Requires-Dist: rich
Requires-Dist: sphobjinv
Requires-Dist: typing-extensions
Requires-Dist: tyro
Requires-Dist: uv
